{
  "cid": "8e564b17eab789f9c6eac0e7e1bea7b8ba22b76353cc61306848bf530237e6e7",
  "note": "Stub citation — bytes not yet mirrored. /c/<cid> redirects readers to the upstream URL until the mirror script runs (Week 2+). The hash is computed over the `canonical` sub-object and verifies via lib/cid.ts.",
  "canonical": {
    "capturedAt": "2026-05-27",
    "license": "U.S. Government work — public domain. Attribution recommended.",
    "name": "NLM DailyMed",
    "sourceId": "dailymed",
    "status": "stub",
    "url": "https://dailymed.nlm.nih.gov/dailymed/search.cfm?query=methylprednisolone"
  },
  "probes": [
    {
      "probedAt": "2026-05-27T09:17:35.983Z",
      "method": "GET",
      "httpStatus": 200,
      "finalUrl": "https://dailymed.nlm.nih.gov/dailymed/search.cfm?query=methylprednisolone",
      "contentType": "text/html; charset=utf-8",
      "contentLength": 146521,
      "lastModified": null,
      "etag": null,
      "bodyHashSha256": "664009fd76c482bf33096eedb2ce95d2cf12590e988f0b8d1e269e985f216213",
      "note": "Body hash is a snapshot at probedAt. For dynamic pages (e.g. search results) the hash will differ on later fetches — that is information, not error. Original body bytes are NOT stored (copyright-safe)."
    }
  ]
}
